memory_forward/__init__.py
memory_forward/cli.py
memory_forward/app/__init__.py
memory_forward/app/goodbye.py
memory_forward/app/hello.py
memory_forward-0.0.1a9.dist-info/LICENSE
memory_forward-0.0.1a9.dist-info/METADATA
memory_forward-0.0.1a9.dist-info/WHEEL
memory_forward-0.0.1a9.dist-info/entry_points.txt
memory_forward-0.0.1a9.dist-info/top_level.txt
memory_forward-0.0.1a9.dist-info/RECORD
